si_openaccess/__init__.py
si_openaccess/si_openaccess.py
si_openaccess-0.1.1.dist-info/METADATA
si_openaccess-0.1.1.dist-info/WHEEL
si_openaccess-0.1.1.dist-info/licenses/LICENSE
si_openaccess-0.1.1.dist-info/RECORD
