Metadata-Version: 2.1
Name: si_openaccess
Version: 0.1.1
Summary: Python module to query the Smithsonian Institution Open Access API.
Project-URL: Homepage, https://github.com/Smithsonian/smithsonian-openaccess
Project-URL: Bug Tracker, https://github.com/Smithsonian/smithsonian-openaccess/issues
Author-email: "Luis J. Villanueva" <villanueval@si.edu>
License-File: LICENSE
Classifier: License :: OSI Approved :: Apache Software License
Classifier: Operating System :: OS Independent
Classifier: Programming Language :: Python :: 3
Requires-Python: >=3.11
Requires-Dist: requests
